rouzbehthebatman/__init__.py
rouzbehthebatman/clustering.py
rouzbehthebatman/preprocessing.py
rouzbehthebatman-0.1.2.dist-info/LICENSE
rouzbehthebatman-0.1.2.dist-info/METADATA
rouzbehthebatman-0.1.2.dist-info/WHEEL
rouzbehthebatman-0.1.2.dist-info/RECORD
